tickrtape/.DS_Store
tickrtape/__init__.py
tickrtape-0.1.5.dist-info/WHEEL
tickrtape-0.1.5.dist-info/METADATA
tickrtape-0.1.5.dist-info/RECORD
